AUTHORS.rst
CONTRIBUTING.rst
HISTORY.rst
LICENSE
MANIFEST.in
README.rst
setup.cfg
setup.py
anapioficeandfire/__init__.py
anapioficeandfire/api.py
anapioficeandfire/binder.py
anapioficeandfire/cursor.py
anapioficeandfire/error.py
anapioficeandfire/models.py
anapioficeandfire/parsers.py
anapioficeandfire/utils.py
anapioficeandfire.egg-info/PKG-INFO
anapioficeandfire.egg-info/SOURCES.txt
anapioficeandfire.egg-info/dependency_links.txt
anapioficeandfire.egg-info/not-zip-safe
anapioficeandfire.egg-info/requires.txt
anapioficeandfire.egg-info/top_level.txt
docs/Makefile
docs/authors.rst
docs/conf.py
docs/contributing.rst
docs/getting_started.rst
docs/history.rst
docs/index.rst
docs/installation.rst
docs/make.bat
docs/usage.rst
tests/configuration.py
tests/test_api.py