Metadata-Version: 1.1
Name: anapioficeandfire
Version: 0.1.2
Summary: A Python helper library for anapioficeandfire.com
Home-page: https://github.com/joakimskoog/anapioficeandfire-python
Author: Joakim Skoog
Author-email: joakimskooog@gmail.com
License: BSD
Keywords: anapioficeandfire
Platform: UNKNOWN
Classifier: Development Status :: 2 - Pre-Alpha
Classifier: Intended Audience :: Developers
Classifier: License :: OSI Approved :: BSD License
Classifier: Natural Language :: English
Classifier: Programming Language :: Python :: 2
Classifier: Programming Language :: Python :: 2.6
Classifier: Programming Language :: Python :: 2.7
Classifier: Programming Language :: Python :: 3
Classifier: Programming Language :: Python :: 3.3
Classifier: Programming Language :: Python :: 3.4
Classifier: Programming Language :: Python :: 3.5
